{
    "key": "group_603e0e7b77aa6",
    "title": "Page - Galeria",
    "fields": [],
    "location": [
        [
            {
                "param": "post_template",
                "operator": "==",
                "value": "template-galeria.php"
            }
        ]
    ],
    "menu_order": 0,
    "position": "normal",
    "style": "default",
    "label_placement": "top",
    "instruction_placement": "label",
    "hide_on_screen": "",
    "active": true,
    "description": "",
    "modified": 1614888993
}